howfast_apm/__init__.py
howfast_apm/config.py
howfast_apm/core.py
howfast_apm/flask.py
howfast_apm/hook_requests.py
howfast_apm/queue.py
howfast_apm/runner.py
howfast_apm/utils.py
howfast_apm-0.8.0.dist-info/LICENSE
howfast_apm-0.8.0.dist-info/METADATA
howfast_apm-0.8.0.dist-info/WHEEL
howfast_apm-0.8.0.dist-info/RECORD
