Metadata-Version: 2.1
Name: howfast-apm
Version: 0.8.0
Summary: Lightweight Application Performance Monitoring middleware that measures and reports performance data to HowFast APM.
Home-page: https://github.com/HowFast/apm-python
License: MIT
Keywords: apm,performance,timing,howfast
Author: Mickaël Bergem
Author-email: mickael@howfast.tech
Requires-Python: >=3.9.20,<3.13
Classifier: Development Status :: 4 - Beta
Classifier: Framework :: Flask
Classifier: Intended Audience :: Developers
Classifier: License :: OSI Approved :: MIT License
Classifier: Programming Language :: Python :: 3
Classifier: Programming Language :: Python :: 3.10
Classifier: Programming Language :: Python :: 3.11
Classifier: Programming Language :: Python :: 3.12
Classifier: Topic :: Software Development :: Build Tools
Provides-Extra: flask
Requires-Dist: blinker (>=1.1) ; extra == "flask"
Requires-Dist: flask (>=0.8) ; extra == "flask"
Requires-Dist: requests (>=2.22)
Requires-Dist: werkzeug (>=0.7) ; extra == "flask"
